{"version":"1.2.0","artifactCoordinates":{"groupId":"org.mule.connectors","artifactId":"mule-sockets-connector","version":"1.2.1","type":"jar","classifier":"mule-plugin"},"dependencies":[{"artifactCoordinates":{"groupId":"commons-io","artifactId":"commons-io","version":"2.8.0","type":"jar"},"uri":"repository/commons-io/commons-io/2.8.0/commons-io-2.8.0.jar","packages":["org.apache.commons.io","org.apache.commons.io.comparator","org.apache.commons.io.file","org.apache.commons.io.filefilter","org.apache.commons.io.function","org.apache.commons.io.input","org.apache.commons.io.input.buffer","org.apache.commons.io.monitor","org.apache.commons.io.output","org.apache.commons.io.serialization"],"resources":["META-INF/LICENSE.txt","META-INF/MANIFEST.MF","META-INF/NOTICE.txt","META-INF/maven/commons-io/commons-io/pom.properties","META-INF/maven/commons-io/commons-io/pom.xml"]},{"artifactCoordinates":{"groupId":"org.apache.commons","artifactId":"commons-lang3","version":"3.11","type":"jar"},"uri":"repository/org/apache/commons/commons-lang3/3.11/commons-lang3-3.11.jar","packages":["org.apache.commons.lang3","org.apache.commons.lang3.arch","org.apache.commons.lang3.builder","org.apache.commons.lang3.compare","org.apache.commons.lang3.concurrent","org.apache.commons.lang3.concurrent.locks","org.apache.commons.lang3.event","org.apache.commons.lang3.exception","org.apache.commons.lang3.function","org.apache.commons.lang3.math","org.apache.commons.lang3.mutable","org.apache.commons.lang3.reflect","org.apache.commons.lang3.stream","org.apache.commons.lang3.text","org.apache.commons.lang3.text.translate","org.apache.commons.lang3.time","org.apache.commons.lang3.tuple"],"resources":["META-INF/LICENSE.txt","META-INF/MANIFEST.MF","META-INF/NOTICE.txt","META-INF/maven/org.apache.commons/commons-lang3/pom.properties","META-INF/maven/org.apache.commons/commons-lang3/pom.xml"]}],"packages":["org.mule.extension.socket.api","org.mule.extension.socket.api.client","org.mule.extension.socket.api.config","org.mule.extension.socket.api.connection","org.mule.extension.socket.api.connection.tcp","org.mule.extension.socket.api.connection.tcp.protocol","org.mule.extension.socket.api.connection.udp","org.mule.extension.socket.api.exceptions","org.mule.extension.socket.api.provider.tcp","org.mule.extension.socket.api.provider.udp","org.mule.extension.socket.api.socket","org.mule.extension.socket.api.socket.factory","org.mule.extension.socket.api.socket.tcp","org.mule.extension.socket.api.socket.udp","org.mule.extension.socket.api.source","org.mule.extension.socket.api.worker","org.mule.extension.socket.internal"],"resources":["META-INF/maven/org.mule.connectors/mule-sockets-connector/pom.xml","META-INF/mule-artifact/icon.svg","META-INF/mule-artifact/mule-artifact.json","META-INF/sockets-extension-descriptions.xml"]}